drf_excel_export/__init__.py
drf_excel_export/export.py
drf_excel_export/utils.py
drf_excel_export/management/__init__.py
drf_excel_export/management/commands/__init__.py
drf_excel_export/management/commands/export_excel.py
drf_excel_export-0.1.3.dist-info/LICENSE
drf_excel_export-0.1.3.dist-info/METADATA
drf_excel_export-0.1.3.dist-info/WHEEL
drf_excel_export-0.1.3.dist-info/top_level.txt
drf_excel_export-0.1.3.dist-info/RECORD
