Metadata-Version: 2.1
Name: drf-excel-export
Version: 0.1.3
Summary: A tool to export Django REST Framework API documentation to Excel
Home-page: https://github.com/donaldte/drf-excel-export
Author: Donald Programmeur
Author-email: donaldtedom0@gmail.com
Classifier: Programming Language :: Python :: 3
Classifier: License :: OSI Approved :: MIT License
Classifier: Operating System :: OS Independent
Requires-Python: >=3.6
License-File: LICENSE
